{"items":[{"title":"100个关键词回顾党史100年","link":"https://m.weibo.cn/search?containerid=100103type%3D1%26q%3D100%E4%B8%AA%E5%85%B3%E9%94%AE%E8%AF%8D%E5%9B%9E%E9%A1%BE%E5%85%9A%E5%8F%B2100%E5%B9%B4","content":"100个关键词回顾党史100年","contentSnippet":"100个关键词回顾党史100年","guid":"https://m.weibo.cn/search?containerid=100103type%3D1%26q%3D100%E4%B8%AA%E5%85%B3%E9%94%AE%E8%AF%8D%E5%9B%9E%E9%A1%BE%E5%85%9A%E5%8F%B2100%E5%B9%B4"},{"title":"刘昊然敲车窗","link":"https://m.weibo.cn/search?containerid=100103type%3D1%26q%3D%E5%88%98%E6%98%8A%E7%84%B6%E6%95%B2%E8%BD%A6%E7%AA%97","content":"刘昊然敲车窗","contentSnippet":"刘昊然敲车窗","guid":"https://m.weibo.cn/search?containerid=100103type%3D1%26q%3D%E5%88%98%E6%98%8A%E7%84%B6%E6%95%B2%E8%BD%A6%E7%AA%97"},{"title":"小伙住ICU95天医护写1.1万字日记鼓励","link":"https://m.weibo.cn/search?containerid=100103type%3D1%26q%3D%E5%B0%8F%E4%BC%99%E4%BD%8FICU95%E5%A4%A9%E5%8C%BB%E6%8A%A4%E5%86%991.1%E4%B8%87%E5%AD%97%E6%97%A5%E8%AE%B0%E9%BC%93%E5%8A%B1","content":"小伙住ICU95天医护写1.1万字日记鼓励","contentSnippet":"小伙住ICU95天医护写1.1万字日记鼓励","guid":"https://m.weibo.cn/search?containerid=100103type%3D1%26q%3D%E5%B0%8F%E4%BC%99%E4%BD%8FICU95%E5%A4%A9%E5%8C%BB%E6%8A%A4%E5%86%991.1%E4%B8%87%E5%AD%97%E6%97%A5%E8%AE%B0%E9%BC%93%E5%8A%B1"},{"title":"英语四级","link":"https://m.weibo.cn/search?containerid=100103type%3D1%26q%3D%E8%8B%B1%E8%AF%AD%E5%9B%9B%E7%BA%A7","content":"英语四级","contentSnippet":"英语四级","guid":"https://m.weibo.cn/search?containerid=100103type%3D1%26q%3D%E8%8B%B1%E8%AF%AD%E5%9B%9B%E7%BA%A7"},{"title":"六级","link":"https://m.weibo.cn/search?containerid=100103type%3D1%26q%3D%E5%85%AD%E7%BA%A7","content":"六级","contentSnippet":"六级","guid":"https://m.weibo.cn/search?containerid=100103type%3D1%26q%3D%E5%85%AD%E7%BA%A7"},{"title":"把院长派来的博士当成骗子","link":"https://m.weibo.cn/search?containerid=100103type%3D1%26q%3D%E6%8A%8A%E9%99%A2%E9%95%BF%E6%B4%BE%E6%9D%A5%E7%9A%84%E5%8D%9A%E5%A3%AB%E5%BD%93%E6%88%90%E9%AA%97%E5%AD%90","content":"把院长派来的博士当成骗子","contentSnippet":"把院长派来的博士当成骗子","guid":"https://m.weibo.cn/search?containerid=100103type%3D1%26q%3D%E6%8A%8A%E9%99%A2%E9%95%BF%E6%B4%BE%E6%9D%A5%E7%9A%84%E5%8D%9A%E5%A3%AB%E5%BD%93%E6%88%90%E9%AA%97%E5%AD%90"},{"title":"四级翻译 铁观音","link":"https://m.weibo.cn/search?containerid=100103type%3D1%26q%3D%E5%9B%9B%E7%BA%A7%E7%BF%BB%E8%AF%91%20%E9%93%81%E8%A7%82%E9%9F%B3","content":"四级翻译 铁观音","contentSnippet":"四级翻译 铁观音","guid":"https://m.weibo.cn/search?containerid=100103type%3D1%26q%3D%E5%9B%9B%E7%BA%A7%E7%BF%BB%E8%AF%91%20%E9%93%81%E8%A7%82%E9%9F%B3"},{"title":"看热带往事不敢大声呼吸","link":"https://m.weibo.cn/search?containerid=100103type%3D1%26q%3D%E7%9C%8B%E7%83%AD%E5%B8%A6%E5%BE%80%E4%BA%8B%E4%B8%8D%E6%95%A2%E5%A4%A7%E5%A3%B0%E5%91%BC%E5%90%B8","content":"看热带往事不敢大声呼吸","contentSnippet":"看热带往事不敢大声呼吸","guid":"https://m.weibo.cn/search?containerid=100103type%3D1%26q%3D%E7%9C%8B%E7%83%AD%E5%B8%A6%E5%BE%80%E4%BA%8B%E4%B8%8D%E6%95%A2%E5%A4%A7%E5%A3%B0%E5%91%BC%E5%90%B8"},{"title":"宋妍霏爸爸年轻时的照片","link":"https://m.weibo.cn/search?containerid=100103type%3D1%26q%3D%E5%AE%8B%E5%A6%8D%E9%9C%8F%E7%88%B8%E7%88%B8%E5%B9%B4%E8%BD%BB%E6%97%B6%E7%9A%84%E7%85%A7%E7%89%87","content":"宋妍霏爸爸年轻时的照片","contentSnippet":"宋妍霏爸爸年轻时的照片","guid":"https://m.weibo.cn/search?containerid=100103type%3D1%26q%3D%E5%AE%8B%E5%A6%8D%E9%9C%8F%E7%88%B8%E7%88%B8%E5%B9%B4%E8%BD%BB%E6%97%B6%E7%9A%84%E7%85%A7%E7%89%87"},{"title":"顶楼3 全员双胞胎","link":"https://m.weibo.cn/search?containerid=100103type%3D1%26q%3D%E9%A1%B6%E6%A5%BC3%20%E5%85%A8%E5%91%98%E5%8F%8C%E8%83%9E%E8%83%8E","content":"顶楼3 全员双胞胎","contentSnippet":"顶楼3 全员双胞胎","guid":"https://m.weibo.cn/search?containerid=100103type%3D1%26q%3D%E9%A1%B6%E6%A5%BC3%20%E5%85%A8%E5%91%98%E5%8F%8C%E8%83%9E%E8%83%8E"},{"title":"山东曹县人才政策","link":"https://m.weibo.cn/search?containerid=100103type%3D1%26q%3D%E5%B1%B1%E4%B8%9C%E6%9B%B9%E5%8E%BF%E4%BA%BA%E6%89%8D%E6%94%BF%E7%AD%96","content":"山东曹县人才政策","contentSnippet":"山东曹县人才政策","guid":"https://m.weibo.cn/search?containerid=100103type%3D1%26q%3D%E5%B1%B1%E4%B8%9C%E6%9B%B9%E5%8E%BF%E4%BA%BA%E6%89%8D%E6%94%BF%E7%AD%96"},{"title":"杨洁篪就涉疆涉港问题表明严正立场","link":"https://m.weibo.cn/search?containerid=100103type%3D1%26q%3D%E6%9D%A8%E6%B4%81%E7%AF%AA%E5%B0%B1%E6%B6%89%E7%96%86%E6%B6%89%E6%B8%AF%E9%97%AE%E9%A2%98%E8%A1%A8%E6%98%8E%E4%B8%A5%E6%AD%A3%E7%AB%8B%E5%9C%BA","content":"杨洁篪就涉疆涉港问题表明严正立场","contentSnippet":"杨洁篪就涉疆涉港问题表明严正立场","guid":"https://m.weibo.cn/search?containerid=100103type%3D1%26q%3D%E6%9D%A8%E6%B4%81%E7%AF%AA%E5%B0%B1%E6%B6%89%E7%96%86%E6%B6%89%E6%B8%AF%E9%97%AE%E9%A2%98%E8%A1%A8%E6%98%8E%E4%B8%A5%E6%AD%A3%E7%AB%8B%E5%9C%BA"},{"title":"莫文蔚 杜嘉班纳","link":"https://m.weibo.cn/search?containerid=100103type%3D1%26q%3D%E8%8E%AB%E6%96%87%E8%94%9A%20%E6%9D%9C%E5%98%89%E7%8F%AD%E7%BA%B3","content":"莫文蔚 杜嘉班纳","contentSnippet":"莫文蔚 杜嘉班纳","guid":"https://m.weibo.cn/search?containerid=100103type%3D1%26q%3D%E8%8E%AB%E6%96%87%E8%94%9A%20%E6%9D%9C%E5%98%89%E7%8F%AD%E7%BA%B3"},{"title":"广西发现首例印度变异株","link":"https://m.weibo.cn/search?containerid=100103type%3D1%26q%3D%E5%B9%BF%E8%A5%BF%E5%8F%91%E7%8E%B0%E9%A6%96%E4%BE%8B%E5%8D%B0%E5%BA%A6%E5%8F%98%E5%BC%82%E6%A0%AA","content":"广西发现首例印度变异株","contentSnippet":"广西发现首例印度变异株","guid":"https://m.weibo.cn/search?containerid=100103type%3D1%26q%3D%E5%B9%BF%E8%A5%BF%E5%8F%91%E7%8E%B0%E9%A6%96%E4%BE%8B%E5%8D%B0%E5%BA%A6%E5%8F%98%E5%BC%82%E6%A0%AA"},{"title":"有需要打疫苗的喵喵喵吗","link":"https://m.weibo.cn/search?containerid=100103type%3D1%26q%3D%E6%9C%89%E9%9C%80%E8%A6%81%E6%89%93%E7%96%AB%E8%8B%97%E7%9A%84%E5%96%B5%E5%96%B5%E5%96%B5%E5%90%97","content":"有需要打疫苗的喵喵喵吗","contentSnippet":"有需要打疫苗的喵喵喵吗","guid":"https://m.weibo.cn/search?containerid=100103type%3D1%26q%3D%E6%9C%89%E9%9C%80%E8%A6%81%E6%89%93%E7%96%AB%E8%8B%97%E7%9A%84%E5%96%B5%E5%96%B5%E5%96%B5%E5%90%97"},{"title":"广州夫妇隐瞒中高风险地旅居史被立案侦查","link":"https://m.weibo.cn/search?containerid=100103type%3D1%26q%3D%E5%B9%BF%E5%B7%9E%E5%A4%AB%E5%A6%87%E9%9A%90%E7%9E%92%E4%B8%AD%E9%AB%98%E9%A3%8E%E9%99%A9%E5%9C%B0%E6%97%85%E5%B1%85%E5%8F%B2%E8%A2%AB%E7%AB%8B%E6%A1%88%E4%BE%A6%E6%9F%A5","content":"广州夫妇隐瞒中高风险地旅居史被立案侦查","contentSnippet":"广州夫妇隐瞒中高风险地旅居史被立案侦查","guid":"https://m.weibo.cn/search?containerid=100103type%3D1%26q%3D%E5%B9%BF%E5%B7%9E%E5%A4%AB%E5%A6%87%E9%9A%90%E7%9E%92%E4%B8%AD%E9%AB%98%E9%A3%8E%E9%99%A9%E5%9C%B0%E6%97%85%E5%B1%85%E5%8F%B2%E8%A2%AB%E7%AB%8B%E6%A1%88%E4%BE%A6%E6%9F%A5"},{"title":"选择可以改写命运吗","link":"https://m.weibo.cn/search?containerid=100103type%3D1%26q%3D%E9%80%89%E6%8B%A9%E5%8F%AF%E4%BB%A5%E6%94%B9%E5%86%99%E5%91%BD%E8%BF%90%E5%90%97","content":"选择可以改写命运吗","contentSnippet":"选择可以改写命运吗","guid":"https://m.weibo.cn/search?containerid=100103type%3D1%26q%3D%E9%80%89%E6%8B%A9%E5%8F%AF%E4%BB%A5%E6%94%B9%E5%86%99%E5%91%BD%E8%BF%90%E5%90%97"},{"title":"江豚妈妈背着江豚宝宝戏水","link":"https://m.weibo.cn/search?containerid=100103type%3D1%26q%3D%E6%B1%9F%E8%B1%9A%E5%A6%88%E5%A6%88%E8%83%8C%E7%9D%80%E6%B1%9F%E8%B1%9A%E5%AE%9D%E5%AE%9D%E6%88%8F%E6%B0%B4","content":"江豚妈妈背着江豚宝宝戏水","contentSnippet":"江豚妈妈背着江豚宝宝戏水","guid":"https://m.weibo.cn/search?containerid=100103type%3D1%26q%3D%E6%B1%9F%E8%B1%9A%E5%A6%88%E5%A6%88%E8%83%8C%E7%9D%80%E6%B1%9F%E8%B1%9A%E5%AE%9D%E5%AE%9D%E6%88%8F%E6%B0%B4"},{"title":"四级听力","link":"https://m.weibo.cn/search?containerid=100103type%3D1%26q%3D%E5%9B%9B%E7%BA%A7%E5%90%AC%E5%8A%9B","content":"四级听力","contentSnippet":"四级听力","guid":"https://m.weibo.cn/search?containerid=100103type%3D1%26q%3D%E5%9B%9B%E7%BA%A7%E5%90%AC%E5%8A%9B"},{"title":"英语四级作文","link":"https://m.weibo.cn/search?containerid=100103type%3D1%26q%3D%E8%8B%B1%E8%AF%AD%E5%9B%9B%E7%BA%A7%E4%BD%9C%E6%96%87","content":"英语四级作文","contentSnippet":"英语四级作文","guid":"https://m.weibo.cn/search?containerid=100103type%3D1%26q%3D%E8%8B%B1%E8%AF%AD%E5%9B%9B%E7%BA%A7%E4%BD%9C%E6%96%87"},{"title":"宋妍霏是tony老师吧","link":"https://m.weibo.cn/search?containerid=100103type%3D1%26q%3D%E5%AE%8B%E5%A6%8D%E9%9C%8F%E6%98%AFtony%E8%80%81%E5%B8%88%E5%90%A7","content":"宋妍霏是tony老师吧","contentSnippet":"宋妍霏是tony老师吧","guid":"https://m.weibo.cn/search?containerid=100103type%3D1%26q%3D%E5%AE%8B%E5%A6%8D%E9%9C%8F%E6%98%AFtony%E8%80%81%E5%B8%88%E5%90%A7"},{"title":"救护车鸣笛遭教练车阻挡4公里","link":"https://m.weibo.cn/search?containerid=100103type%3D1%26q%3D%E6%95%91%E6%8A%A4%E8%BD%A6%E9%B8%A3%E7%AC%9B%E9%81%AD%E6%95%99%E7%BB%83%E8%BD%A6%E9%98%BB%E6%8C%A14%E5%85%AC%E9%87%8C","content":"救护车鸣笛遭教练车阻挡4公里","contentSnippet":"救护车鸣笛遭教练车阻挡4公里","guid":"https://m.weibo.cn/search?containerid=100103type%3D1%26q%3D%E6%95%91%E6%8A%A4%E8%BD%A6%E9%B8%A3%E7%AC%9B%E9%81%AD%E6%95%99%E7%BB%83%E8%BD%A6%E9%98%BB%E6%8C%A14%E5%85%AC%E9%87%8C"},{"title":"四级答案","link":"https://m.weibo.cn/search?containerid=100103type%3D1%26q%3D%E5%9B%9B%E7%BA%A7%E7%AD%94%E6%A1%88","content":"四级答案","contentSnippet":"四级答案","guid":"https://m.weibo.cn/search?containerid=100103type%3D1%26q%3D%E5%9B%9B%E7%BA%A7%E7%AD%94%E6%A1%88"},{"title":"大S ins","link":"https://m.weibo.cn/search?containerid=100103type%3D1%26q%3D%E5%A4%A7S%20ins","content":"大S ins","contentSnippet":"大S ins","guid":"https://m.weibo.cn/search?containerid=100103type%3D1%26q%3D%E5%A4%A7S%20ins"},{"title":"新疆天空一半乳状云一半蓝天","link":"https://m.weibo.cn/search?containerid=100103type%3D1%26q%3D%E6%96%B0%E7%96%86%E5%A4%A9%E7%A9%BA%E4%B8%80%E5%8D%8A%E4%B9%B3%E7%8A%B6%E4%BA%91%E4%B8%80%E5%8D%8A%E8%93%9D%E5%A4%A9","content":"新疆天空一半乳状云一半蓝天","contentSnippet":"新疆天空一半乳状云一半蓝天","guid":"https://m.weibo.cn/search?containerid=100103type%3D1%26q%3D%E6%96%B0%E7%96%86%E5%A4%A9%E7%A9%BA%E4%B8%80%E5%8D%8A%E4%B9%B3%E7%8A%B6%E4%BA%91%E4%B8%80%E5%8D%8A%E8%93%9D%E5%A4%A9"},{"title":"微博电影之夜全阵容","link":"https://m.weibo.cn/search?containerid=100103type%3D1%26q%3D%E5%BE%AE%E5%8D%9A%E7%94%B5%E5%BD%B1%E4%B9%8B%E5%A4%9C%E5%85%A8%E9%98%B5%E5%AE%B9","content":"微博电影之夜全阵容","contentSnippet":"微博电影之夜全阵容","guid":"https://m.weibo.cn/search?containerid=100103type%3D1%26q%3D%E5%BE%AE%E5%8D%9A%E7%94%B5%E5%BD%B1%E4%B9%8B%E5%A4%9C%E5%85%A8%E9%98%B5%E5%AE%B9"},{"title":"1头小象遇险3头大象救援","link":"https://m.weibo.cn/search?containerid=100103type%3D1%26q%3D1%E5%A4%B4%E5%B0%8F%E8%B1%A1%E9%81%87%E9%99%A93%E5%A4%B4%E5%A4%A7%E8%B1%A1%E6%95%91%E6%8F%B4","content":"1头小象遇险3头大象救援","contentSnippet":"1头小象遇险3头大象救援","guid":"https://m.weibo.cn/search?containerid=100103type%3D1%26q%3D1%E5%A4%B4%E5%B0%8F%E8%B1%A1%E9%81%87%E9%99%A93%E5%A4%B4%E5%A4%A7%E8%B1%A1%E6%95%91%E6%8F%B4"},{"title":"美国计划销毁约千万剂强生新冠疫苗","link":"https://m.weibo.cn/search?containerid=100103type%3D1%26q%3D%E7%BE%8E%E5%9B%BD%E8%AE%A1%E5%88%92%E9%94%80%E6%AF%81%E7%BA%A6%E5%8D%83%E4%B8%87%E5%89%82%E5%BC%BA%E7%94%9F%E6%96%B0%E5%86%A0%E7%96%AB%E8%8B%97","content":"美国计划销毁约千万剂强生新冠疫苗","contentSnippet":"美国计划销毁约千万剂强生新冠疫苗","guid":"https://m.weibo.cn/search?containerid=100103type%3D1%26q%3D%E7%BE%8E%E5%9B%BD%E8%AE%A1%E5%88%92%E9%94%80%E6%AF%81%E7%BA%A6%E5%8D%83%E4%B8%87%E5%89%82%E5%BC%BA%E7%94%9F%E6%96%B0%E5%86%A0%E7%96%AB%E8%8B%97"},{"title":"大s 狠话是保留的","link":"https://m.weibo.cn/search?containerid=100103type%3D1%26q%3D%E5%A4%A7s%20%E7%8B%A0%E8%AF%9D%E6%98%AF%E4%BF%9D%E7%95%99%E7%9A%84","content":"大s 狠话是保留的","contentSnippet":"大s 狠话是保留的","guid":"https://m.weibo.cn/search?containerid=100103type%3D1%26q%3D%E5%A4%A7s%20%E7%8B%A0%E8%AF%9D%E6%98%AF%E4%BF%9D%E7%95%99%E7%9A%84"},{"title":"让你包粽子不是绑架粽子","link":"https://m.weibo.cn/search?containerid=100103type%3D1%26q%3D%E8%AE%A9%E4%BD%A0%E5%8C%85%E7%B2%BD%E5%AD%90%E4%B8%8D%E6%98%AF%E7%BB%91%E6%9E%B6%E7%B2%BD%E5%AD%90","content":"让你包粽子不是绑架粽子","contentSnippet":"让你包粽子不是绑架粽子","guid":"https://m.weibo.cn/search?containerid=100103type%3D1%26q%3D%E8%AE%A9%E4%BD%A0%E5%8C%85%E7%B2%BD%E5%AD%90%E4%B8%8D%E6%98%AF%E7%BB%91%E6%9E%B6%E7%B2%BD%E5%AD%90"},{"title":"人的新陈代谢原来这么震撼","link":"https://m.weibo.cn/search?containerid=100103type%3D1%26q%3D%E4%BA%BA%E7%9A%84%E6%96%B0%E9%99%88%E4%BB%A3%E8%B0%A2%E5%8E%9F%E6%9D%A5%E8%BF%99%E4%B9%88%E9%9C%87%E6%92%BC","content":"人的新陈代谢原来这么震撼","contentSnippet":"人的新陈代谢原来这么震撼","guid":"https://m.weibo.cn/search?containerid=100103type%3D1%26q%3D%E4%BA%BA%E7%9A%84%E6%96%B0%E9%99%88%E4%BB%A3%E8%B0%A2%E5%8E%9F%E6%9D%A5%E8%BF%99%E4%B9%88%E9%9C%87%E6%92%BC"},{"title":"台风预警","link":"https://m.weibo.cn/search?containerid=100103type%3D1%26q%3D%E5%8F%B0%E9%A3%8E%E9%A2%84%E8%AD%A6","content":"台风预警","contentSnippet":"台风预警","guid":"https://m.weibo.cn/search?containerid=100103type%3D1%26q%3D%E5%8F%B0%E9%A3%8E%E9%A2%84%E8%AD%A6"},{"title":"国足5比0马尔代夫","link":"https://m.weibo.cn/search?containerid=100103type%3D1%26q%3D%E5%9B%BD%E8%B6%B35%E6%AF%940%E9%A9%AC%E5%B0%94%E4%BB%A3%E5%A4%AB","content":"国足5比0马尔代夫","contentSnippet":"国足5比0马尔代夫","guid":"https://m.weibo.cn/search?containerid=100103type%3D1%26q%3D%E5%9B%BD%E8%B6%B35%E6%AF%940%E9%A9%AC%E5%B0%94%E4%BB%A3%E5%A4%AB"},{"title":"cp28","link":"https://m.weibo.cn/search?containerid=100103type%3D1%26q%3Dcp28","content":"cp28","contentSnippet":"cp28","guid":"https://m.weibo.cn/search?containerid=100103type%3D1%26q%3Dcp28"},{"title":"广州疫情防控新闻发布会","link":"https://m.weibo.cn/search?containerid=100103type%3D1%26q%3D%E5%B9%BF%E5%B7%9E%E7%96%AB%E6%83%85%E9%98%B2%E6%8E%A7%E6%96%B0%E9%97%BB%E5%8F%91%E5%B8%83%E4%BC%9A","content":"广州疫情防控新闻发布会","contentSnippet":"广州疫情防控新闻发布会","guid":"https://m.weibo.cn/search?containerid=100103type%3D1%26q%3D%E5%B9%BF%E5%B7%9E%E7%96%AB%E6%83%85%E9%98%B2%E6%8E%A7%E6%96%B0%E9%97%BB%E5%8F%91%E5%B8%83%E4%BC%9A"},{"title":"狗狗咬破白酒桶把自己灌醉","link":"https://m.weibo.cn/search?containerid=100103type%3D1%26q%3D%E7%8B%97%E7%8B%97%E5%92%AC%E7%A0%B4%E7%99%BD%E9%85%92%E6%A1%B6%E6%8A%8A%E8%87%AA%E5%B7%B1%E7%81%8C%E9%86%89","content":"狗狗咬破白酒桶把自己灌醉","contentSnippet":"狗狗咬破白酒桶把自己灌醉","guid":"https://m.weibo.cn/search?containerid=100103type%3D1%26q%3D%E7%8B%97%E7%8B%97%E5%92%AC%E7%A0%B4%E7%99%BD%E9%85%92%E6%A1%B6%E6%8A%8A%E8%87%AA%E5%B7%B1%E7%81%8C%E9%86%89"},{"title":"陈卓璇想开万人演唱会","link":"https://m.weibo.cn/search?containerid=100103type%3D1%26q%3D%E9%99%88%E5%8D%93%E7%92%87%E6%83%B3%E5%BC%80%E4%B8%87%E4%BA%BA%E6%BC%94%E5%94%B1%E4%BC%9A","content":"陈卓璇想开万人演唱会","contentSnippet":"陈卓璇想开万人演唱会","guid":"https://m.weibo.cn/search?containerid=100103type%3D1%26q%3D%E9%99%88%E5%8D%93%E7%92%87%E6%83%B3%E5%BC%80%E4%B8%87%E4%BA%BA%E6%BC%94%E5%94%B1%E4%BC%9A"},{"title":"白银景泰县委原书记坠亡排除他杀","link":"https://m.weibo.cn/search?containerid=100103type%3D1%26q%3D%E7%99%BD%E9%93%B6%E6%99%AF%E6%B3%B0%E5%8E%BF%E5%A7%94%E5%8E%9F%E4%B9%A6%E8%AE%B0%E5%9D%A0%E4%BA%A1%E6%8E%92%E9%99%A4%E4%BB%96%E6%9D%80","content":"白银景泰县委原书记坠亡排除他杀","contentSnippet":"白银景泰县委原书记坠亡排除他杀","guid":"https://m.weibo.cn/search?containerid=100103type%3D1%26q%3D%E7%99%BD%E9%93%B6%E6%99%AF%E6%B3%B0%E5%8E%BF%E5%A7%94%E5%8E%9F%E4%B9%A6%E8%AE%B0%E5%9D%A0%E4%BA%A1%E6%8E%92%E9%99%A4%E4%BB%96%E6%9D%80"},{"title":"郑州早班地铁给乘客送粽子","link":"https://m.weibo.cn/search?containerid=100103type%3D1%26q%3D%E9%83%91%E5%B7%9E%E6%97%A9%E7%8F%AD%E5%9C%B0%E9%93%81%E7%BB%99%E4%B9%98%E5%AE%A2%E9%80%81%E7%B2%BD%E5%AD%90","content":"郑州早班地铁给乘客送粽子","contentSnippet":"郑州早班地铁给乘客送粽子","guid":"https://m.weibo.cn/search?containerid=100103type%3D1%26q%3D%E9%83%91%E5%B7%9E%E6%97%A9%E7%8F%AD%E5%9C%B0%E9%93%81%E7%BB%99%E4%B9%98%E5%AE%A2%E9%80%81%E7%B2%BD%E5%AD%90"},{"title":"台湾疫情","link":"https://m.weibo.cn/search?containerid=100103type%3D1%26q%3D%E5%8F%B0%E6%B9%BE%E7%96%AB%E6%83%85","content":"台湾疫情","contentSnippet":"台湾疫情","guid":"https://m.weibo.cn/search?containerid=100103type%3D1%26q%3D%E5%8F%B0%E6%B9%BE%E7%96%AB%E6%83%85"},{"title":"毕业后重回母校是什么感觉","link":"https://m.weibo.cn/search?containerid=100103type%3D1%26q%3D%E6%AF%95%E4%B8%9A%E5%90%8E%E9%87%8D%E5%9B%9E%E6%AF%8D%E6%A0%A1%E6%98%AF%E4%BB%80%E4%B9%88%E6%84%9F%E8%A7%89","content":"毕业后重回母校是什么感觉","contentSnippet":"毕业后重回母校是什么感觉","guid":"https://m.weibo.cn/search?containerid=100103type%3D1%26q%3D%E6%AF%95%E4%B8%9A%E5%90%8E%E9%87%8D%E5%9B%9E%E6%AF%8D%E6%A0%A1%E6%98%AF%E4%BB%80%E4%B9%88%E6%84%9F%E8%A7%89"},{"title":"3秒徒手扎发","link":"https://m.weibo.cn/search?containerid=100103type%3D1%26q%3D3%E7%A7%92%E5%BE%92%E6%89%8B%E6%89%8E%E5%8F%91","content":"3秒徒手扎发","contentSnippet":"3秒徒手扎发","guid":"https://m.weibo.cn/search?containerid=100103type%3D1%26q%3D3%E7%A7%92%E5%BE%92%E6%89%8B%E6%89%8E%E5%8F%91"},{"title":"90后小伙用模型还原奶奶家庭院","link":"https://m.weibo.cn/search?containerid=100103type%3D1%26q%3D90%E5%90%8E%E5%B0%8F%E4%BC%99%E7%94%A8%E6%A8%A1%E5%9E%8B%E8%BF%98%E5%8E%9F%E5%A5%B6%E5%A5%B6%E5%AE%B6%E5%BA%AD%E9%99%A2","content":"90后小伙用模型还原奶奶家庭院","contentSnippet":"90后小伙用模型还原奶奶家庭院","guid":"https://m.weibo.cn/search?containerid=100103type%3D1%26q%3D90%E5%90%8E%E5%B0%8F%E4%BC%99%E7%94%A8%E6%A8%A1%E5%9E%8B%E8%BF%98%E5%8E%9F%E5%A5%B6%E5%A5%B6%E5%AE%B6%E5%BA%AD%E9%99%A2"},{"title":"四川端午节假期路况","link":"https://m.weibo.cn/search?containerid=100103type%3D1%26q%3D%E5%9B%9B%E5%B7%9D%E7%AB%AF%E5%8D%88%E8%8A%82%E5%81%87%E6%9C%9F%E8%B7%AF%E5%86%B5","content":"四川端午节假期路况","contentSnippet":"四川端午节假期路况","guid":"https://m.weibo.cn/search?containerid=100103type%3D1%26q%3D%E5%9B%9B%E5%B7%9D%E7%AB%AF%E5%8D%88%E8%8A%82%E5%81%87%E6%9C%9F%E8%B7%AF%E5%86%B5"},{"title":"西安警方发放反诈粽子","link":"https://m.weibo.cn/search?containerid=100103type%3D1%26q%3D%E8%A5%BF%E5%AE%89%E8%AD%A6%E6%96%B9%E5%8F%91%E6%94%BE%E5%8F%8D%E8%AF%88%E7%B2%BD%E5%AD%90","content":"西安警方发放反诈粽子","contentSnippet":"西安警方发放反诈粽子","guid":"https://m.weibo.cn/search?containerid=100103type%3D1%26q%3D%E8%A5%BF%E5%AE%89%E8%AD%A6%E6%96%B9%E5%8F%91%E6%94%BE%E5%8F%8D%E8%AF%88%E7%B2%BD%E5%AD%90"},{"title":"约基奇领取MVP奖杯","link":"https://m.weibo.cn/search?containerid=100103type%3D1%26q%3D%E7%BA%A6%E5%9F%BA%E5%A5%87%E9%A2%86%E5%8F%96MVP%E5%A5%96%E6%9D%AF","content":"约基奇领取MVP奖杯","contentSnippet":"约基奇领取MVP奖杯","guid":"https://m.weibo.cn/search?containerid=100103type%3D1%26q%3D%E7%BA%A6%E5%9F%BA%E5%A5%87%E9%A2%86%E5%8F%96MVP%E5%A5%96%E6%9D%AF"},{"title":"西安高校宿舍楼顶建农场","link":"https://m.weibo.cn/search?containerid=100103type%3D1%26q%3D%E8%A5%BF%E5%AE%89%E9%AB%98%E6%A0%A1%E5%AE%BF%E8%88%8D%E6%A5%BC%E9%A1%B6%E5%BB%BA%E5%86%9C%E5%9C%BA","content":"西安高校宿舍楼顶建农场","contentSnippet":"西安高校宿舍楼顶建农场","guid":"https://m.weibo.cn/search?containerid=100103type%3D1%26q%3D%E8%A5%BF%E5%AE%89%E9%AB%98%E6%A0%A1%E5%AE%BF%E8%88%8D%E6%A5%BC%E9%A1%B6%E5%BB%BA%E5%86%9C%E5%9C%BA"},{"title":"边工作边考研是什么感受","link":"https://m.weibo.cn/search?containerid=100103type%3D1%26q%3D%E8%BE%B9%E5%B7%A5%E4%BD%9C%E8%BE%B9%E8%80%83%E7%A0%94%E6%98%AF%E4%BB%80%E4%B9%88%E6%84%9F%E5%8F%97","content":"边工作边考研是什么感受","contentSnippet":"边工作边考研是什么感受","guid":"https://m.weibo.cn/search?containerid=100103type%3D1%26q%3D%E8%BE%B9%E5%B7%A5%E4%BD%9C%E8%BE%B9%E8%80%83%E7%A0%94%E6%98%AF%E4%BB%80%E4%B9%88%E6%84%9F%E5%8F%97"},{"title":"药明康德致歉","link":"https://m.weibo.cn/search?containerid=100103type%3D1%26q%3D%E8%8D%AF%E6%98%8E%E5%BA%B7%E5%BE%B7%E8%87%B4%E6%AD%89","content":"药明康德致歉","contentSnippet":"药明康德致歉","guid":"https://m.weibo.cn/search?containerid=100103type%3D1%26q%3D%E8%8D%AF%E6%98%8E%E5%BA%B7%E5%BE%B7%E8%87%B4%E6%AD%89"},{"title":"大货车少8个轮胎还上路行驶","link":"https://m.weibo.cn/search?containerid=100103type%3D1%26q%3D%E5%A4%A7%E8%B4%A7%E8%BD%A6%E5%B0%918%E4%B8%AA%E8%BD%AE%E8%83%8E%E8%BF%98%E4%B8%8A%E8%B7%AF%E8%A1%8C%E9%A9%B6","content":"大货车少8个轮胎还上路行驶","contentSnippet":"大货车少8个轮胎还上路行驶","guid":"https://m.weibo.cn/search?containerid=100103type%3D1%26q%3D%E5%A4%A7%E8%B4%A7%E8%BD%A6%E5%B0%918%E4%B8%AA%E8%BD%AE%E8%83%8E%E8%BF%98%E4%B8%8A%E8%B7%AF%E8%A1%8C%E9%A9%B6"},{"title":"温州疫情","link":"https://m.weibo.cn/search?containerid=100103type%3D1%26q%3D%E6%B8%A9%E5%B7%9E%E7%96%AB%E6%83%85","content":"温州疫情","contentSnippet":"温州疫情","guid":"https://m.weibo.cn/search?containerid=100103type%3D1%26q%3D%E6%B8%A9%E5%B7%9E%E7%96%AB%E6%83%85"},{"title":"麦当劳遭黑客攻击","link":"https://m.weibo.cn/search?containerid=100103type%3D1%26q%3D%E9%BA%A6%E5%BD%93%E5%8A%B3%E9%81%AD%E9%BB%91%E5%AE%A2%E6%94%BB%E5%87%BB","content":"麦当劳遭黑客攻击","contentSnippet":"麦当劳遭黑客攻击","guid":"https://m.weibo.cn/search?containerid=100103type%3D1%26q%3D%E9%BA%A6%E5%BD%93%E5%8A%B3%E9%81%AD%E9%BB%91%E5%AE%A2%E6%94%BB%E5%87%BB"}],"feedUrl":"http://rsshub.app/weibo/search/hot","paginationLinks":{"self":"http://rsshub.app/weibo/search/hot"},"title":"微博热搜榜","description":"实时热点，每分钟更新一次 - Made with love by RSSHub(https://github.com/DIYgod/RSSHub)","webMaster":"i@diygod.me (DIYgod)","generator":"RSSHub","link":"https://s.weibo.com/top/summary?cate=realtimehot","language":"zh-cn","lastBuildDate":"Sat, 12 Jun 2021 03:58:06 GMT","ttl":"60"}